lvm_read.py
lvm_read-1.23.dist-info/METADATA
lvm_read-1.23.dist-info/WHEEL
lvm_read-1.23.dist-info/licenses/LICENSE
lvm_read-1.23.dist-info/RECORD
